{
    "result": {
        "uplinkFrames": [
            {
                "txInfo": {
                    "frequency": 923400000,
                    "dataRate": {
                        "modulation": "LORA",
                        "bandwidth": 125,
                        "spreadFactor": 12,
                        "bitrate": 0
                    },
                    "codeRate": "4/5"
                },
                "rxInfo": [
                    {
                        "mac": "00800000a000151a",
                        "time": "2021-10-18T06:58:20.786715Z",
                        "timeSinceGPSEpoch": "",
                        "timestamp": 226389348,
                        "rssi": -85,
                        "loRaSNR": 6.2,
                        "board": 0,
                        "antenna": 0
                    },
                    {
                        "mac": "00800000a0000a1c",
                        "time": "2021-10-18T07:27:10.614211Z",
                        "timeSinceGPSEpoch": "",
                        "timestamp": 2293539524,
                        "rssi": -96,
                        "loRaSNR": -11.5,
                        "board": 0,
                        "antenna": 0
                    }
                ],
                "phyPayloadJSON": {
                    "mhdr": {
                        "mType": "ConfirmedDataUp",
                        "major": "LoRaWANR1"
                    },
                    "macPayload": {
                        "fhdr": {
                            "devAddr": "06fb67c9",
                            "fCtrl": {
                                "adr": false,
                                "adrAckReq": false,
                                "ack": false,
                                "fPending": false,
                                "classB": false
                            },
                            "fCnt": 162,
                            "fOpts": null
                        },
                        "fPort": 1,
                        "frmPayload": [
                            {
                                "bytes": "0IKB"
                            }
                        ]
                    },
                    "mic": "d45a8fe0"
                }
            }
        ],
        "downlinkFrames": []
    }
}