{
    "result": {
        "uplinkFrames": [
            {
                "txInfo": {
                    "frequency": 923400000,
                    "dataRate": {
                        "modulation": "LORA",
                        "bandwidth": 125,
                        "spreadFactor": 9,
                        "bitrate": 0
                    },
                    "codeRate": "4/5"
                },
                "rxInfo": [
                    {
                        "mac": "00800000a0000ed1",
                        "time": "2021-10-18T08:51:23.568945Z",
                        "timeSinceGPSEpoch": "",
                        "timestamp": 2628915668,
                        "rssi": -88,
                        "loRaSNR": 7.0,
                        "board": 0,
                        "antenna": 0
                    },
                    {
                        "mac": "00800000a0000a1c",
                        "time": "2021-10-18T09:00:38.502889Z",
                        "timeSinceGPSEpoch": "",
                        "timestamp": 3606493052,
                        "rssi": -91,
                        "loRaSNR": -12,
                        "board": 0,
                        "antenna": 0
                    }
                ],
                "phyPayloadJSON": {
                    "mhdr": {
                        "mType": "ConfirmedDataUp",
                        "major": "LoRaWANR1"
                    },
                    "macPayload": {
                        "fhdr": {
                            "devAddr": "06fb67c9",
                            "fCtrl": {
                                "adr": false,
                                "adrAckReq": false,
                                "ack": false,
                                "fPending": false,
                                "classB": false
                            },
                            "fCnt": 529,
                            "fOpts": null
                        },
                        "fPort": 1,
                        "frmPayload": [
                            {
                                "bytes": "07VI"
                            }
                        ]
                    },
                    "mic": "d1827ec1"
                }
            }
        ],
        "downlinkFrames": []
    }
}